rrelu/__init__.py
rrelu/setup.py
rrelu/models/__init__.py
rrelu/models/alexnet.py
rrelu/models/alexnet_cifar100.py
rrelu/models/lenet.py
rrelu/models/resnet.py
rrelu/models/resnet_cifar100.py
rrelu/models/vgg.py
rrelu/models/vgg_cifar100.py
rrelu/pytorchfi/__init__.py
rrelu/pytorchfi/core.py
rrelu/pytorchfi/core_train.py
rrelu/pytorchfi/neuron_error_models.py
rrelu/pytorchfi/util.py
rrelu/pytorchfi/weight_error_models.py
rrelu/relu_bound/__init__.py
rrelu/relu_bound/bound_fitact.py
rrelu/relu_bound/bound_proact.py
rrelu/relu_bound/bound_relu.py
rrelu/relu_bound/bound_tresh.py
rrelu/relu_bound/bound_zero.py
rrelu/search_bound/__init__.py
rrelu/search_bound/fitact.py
rrelu/search_bound/ftclip.py
rrelu/search_bound/proact.py
rrelu/search_bound/ranger.py
rrelu/utils/__init__.py
rrelu/utils/distributed.py
rrelu/utils/init.py
rrelu/utils/lr_scheduler.py
rrelu/utils/metric.py
rrelu/utils/misc.py
rrelu-0.1.0.dist-info/LICENSE.txt
rrelu-0.1.0.dist-info/METADATA
rrelu-0.1.0.dist-info/WHEEL
rrelu-0.1.0.dist-info/top_level.txt
rrelu-0.1.0.dist-info/RECORD
