Metadata-Version: 2.1
Name: rrelu
Version: 0.1.0
Summary: generate reliable relu activation function for DNNs
Home-page: https://github.com/hamidmousavi0/reliable-relu-toolbox
Author: Seyedhamidreza Mousavi
Author-email: Seyedhamidreza Mousavi <seyedhamidreza.mousavi@mdu.se>
Project-URL: Homepage, https://github.com/hamidmousavi0/reliable-relu-toolbox
Project-URL: Issues, https://github.com/hamidmousavi0/reliable-relu-toolbox/issues
Classifier: Programming Language :: Python :: 3
Classifier: License :: OSI Approved :: MIT License
Classifier: Operating System :: OS Independent
Requires-Python: >=3.6
License-File: LICENSE.txt
